psruq/__init__.py
psruq/datasets/__init__.py
psruq/datasets/constants.py
psruq/datasets/datasets.py
psruq/datasets/loaders.py
psruq/datasets/transforms.py
psruq/losses/__init__.py
psruq/losses/constants.py
psruq/losses/losses.py
psruq/metrics/__init__.py
psruq/metrics/central_predictions.py
psruq/metrics/constants.py
psruq/metrics/create_specific_risks.py
psruq/metrics/g_primitives.py
psruq/metrics/getters.py
psruq/metrics/risk_primitives.py
psruq/metrics/utils.py
psruq/models/__init__.py
psruq/models/constants.py
psruq/models/load_models.py
psruq/models/resnet.py
psruq/models/vgg.py
psruq/notebook/__init__.py
psruq/notebook/reliability_diagrams.py
psruq/source/__init__.py
psruq/source/data_utils.py
psruq/source/evaluation_utils.py
psruq/source/extract_logits.py
psruq/source/losses.py
psruq/source/path_config.py
psruq/source/path_utils.py
psruq/source/postprocessing_utils.py
psruq/source/table_utils.py
psruq/source/uncertainty_scores.py
psruq/utils/__init__.py
psruq/utils/general_utils.py
psruq/utils/vector_utils.py
psruq_python-0.0.4.dist-info/METADATA
psruq_python-0.0.4.dist-info/WHEEL
psruq_python-0.0.4.dist-info/RECORD
