Metadata-Version: 2.3
Name: psruq-python
Version: 0.0.4
Summary: Code for uncertainty quantification with proper scoring rules.
Requires-Python: >=3.10
Requires-Dist: bitsandbytes==0.42.0
Requires-Dist: matplotlib>=3.2.2
Requires-Dist: opencv-python>=4.10.0.84
Requires-Dist: pandas>=2.2.2
Requires-Dist: safetensors>=0.4.5
Requires-Dist: scikit-learn>=1.5.2
Requires-Dist: scipy>=1.14.1
Requires-Dist: seaborn>=0.13.2
Requires-Dist: torch-uncertainty
Requires-Dist: torch>=2.4.1
Requires-Dist: torchvision>=0.19.1
Requires-Dist: tqdm>=4.66.5
Provides-Extra: laplace
Requires-Dist: laplace-torch>=0.2.1; extra == 'laplace'
Provides-Extra: notebook
Requires-Dist: ipykernel>=6.29.5; extra == 'notebook'
Requires-Dist: jupyter>=1.1.1; extra == 'notebook'
Requires-Dist: jupyterlab>=4.2.5; extra == 'notebook'
